slock/__init__.py
slock/async_slock.py
slock/base_key.py
slock/slock.py
slock-0.0.3.dist-info/licenses/LICENSE
slock-0.0.3.dist-info/METADATA
slock-0.0.3.dist-info/WHEEL
slock-0.0.3.dist-info/top_level.txt
slock-0.0.3.dist-info/RECORD
