Metadata-Version: 2.4
Name: slock
Version: 0.0.3
Summary: Simplifying concurrency with granular lock management.
Author-email: lisong <lisong.pvt@outlook.com>
License-Expression: MIT
Project-URL: Homepage, https://github.com/gitlisong/slock
Project-URL: Issues, https://github.com/gitlisong/slock/issues
Classifier: Programming Language :: Python :: 3
Classifier: Operating System :: OS Independent
Requires-Python: >=3.8
License-File: LICENSE
Dynamic: license-file
